{
  "name": "Mila Token",
  "symbol": "MILA",
  "description": "Mila is a community-driven meme token on Solana.",
  "image": "https://raw.githubusercontent.com/<KULLANICI_ADIN>/Mila-token/main/logo.png",
  "external_url": "https://mila-token.github.io",
  "seller_fee_basis_points": 0,
  "attributes": [],
  "properties": {
    "files": [
      {
        "uri": "https://raw.githubusercontent.com/<KULLANICI_ADIN>/Mila-token/main/logo.png",
        "type": "image/png"
      }
    ],
    "category": "image",
    "creators": [
      {
        "address": "5NW1QK8YW2ZdJQgnPjar5w1seVfmZRNbUGU4vEDBSH6j",
        "share": 100
      }
    ]
  }
}